Metadata-Version: 1.1
Name: fakebook_server
Version: 0.1.4
Summary: fakebook is a Facebook API simulator meant for test purposes
Home-page: https://github.com/heynemann/fakebook
Author: Bernardo Heynemann
Author-email: heynemann@gmail.com
License: MIT
Keywords: facebook api oauth test
Platform: UNKNOWN
Classifier: Development Status :: 4 - Beta
Classifier: Intended Audience :: Developers
Classifier: License :: OSI Approved :: MIT License
Classifier: Natural Language :: English
Classifier: Operating System :: Unix
Classifier: Programming Language :: Python :: 2.7
Classifier: Operating System :: OS Independent
